gmail_filter_manager/__init__.py
gmail_filter_manager/gfm_extract.py
gmail_filter_manager/gfm_make.py
gmail_filter_manager/py.typed
gmail_filter_manager-0.1.2.dist-info/LICENSE
gmail_filter_manager-0.1.2.dist-info/METADATA
gmail_filter_manager-0.1.2.dist-info/WHEEL
gmail_filter_manager-0.1.2.dist-info/entry_points.txt
gmail_filter_manager-0.1.2.dist-info/RECORD
