Metadata-Version: 2.1
Name: gmail-filter-manager
Version: 0.1.2
Summary: Gmail filer manager using YAML format.
Home-page: https://github.com/rcmdnk/gmail_filter_manager
License: MIT
Keywords: gmail,yaml,cli
Author: rcmdnk
Author-email: rcmdnk@gmail.com
Requires-Python: >=3.8.1,<4.0.0
Classifier: Development Status :: 3 - Alpha
Classifier: Environment :: Console
Classifier: License :: OSI Approved :: MIT License
Classifier: Operating System :: OS Independent
Classifier: Programming Language :: Python :: 3
Classifier: Programming Language :: Python :: 3.9
Classifier: Programming Language :: Python :: 3.10
Classifier: Programming Language :: Python :: 3.11
Classifier: Programming Language :: Python :: 3.12
Classifier: Topic :: Utilities
Requires-Dist: ruamel-yaml (>=0.17.32,<0.18.0)
Project-URL: Repository, https://github.com/rcmdnk/gmail_filter_manager
